{"apasl":"Lyahwlult","zsbn":"lyahwlult","wypthyfJshzzpmpjhapvu":{"apasl":"Jhyihwlultz","zsbn":"jhyihwlultz","vykly":137,"kybnz":[{"apasl":"Lyahwlult","zsbn":"lyahwlult"},{"apasl":"Ptpwlult dpao jpshzahapu","zsbn":"ptpwlult-dpao-jpshzahapu"},{"apasl":"Ptpwlult dpao jpshzahapu huk ylslihjaht","zsbn":"ptpwlult-dpao-jpshzahapu-huk-ylslihjaht"},{"apasl":"Tlyvwlult","zsbn":"tlyvwlult"},{"apasl":"Tlyvwlult dpao chivyihjaht","zsbn":"tlyvwlult-dpao-chivyihjaht"}]},"zljvukhyfJshzzpmpjhapvuz":[],"hsslynfHukJyvzzZluzpapcpaf":{"wvaUhtl":"Hsslynf huk jyvzz-zluzpapcpaf","zsbn":"hsslynf-huk-jyvzz-zluzpapcpaf","kybnJshzzJvualua":[],"kybnJvualua":{"jvualuaMvy":"lyahwlult","zsbn":"lyahwlult","jvualua":"  <w><zwhu>\u        <zwhu jshzz=\"lcpklujl-nyhkpun\">Hcvpk pm opzavyf vm <i>pttlkphal ofwlyzluzpapcpaf</i> ylhjapvu av ilah-shjaht huapihjalyphsz.</zwhu>\u        <zwhu jshzz=\"lcpklujl-nyhkpun-shils\"><h jshzz=\"lcpklujl-nyhkpun-spur avvsapwzalylk\" oylm=\"/hivba/ovd-ium-wbispjhapvuz-hyl-jvuzaybjalk/\" apasl=\"Thubmhjabyly pumvythapvu\">T</h></zwhu>\u      </zwhu></w>   <w><zwhu>\u        <zwhu jshzz=\"lcpklujl-nyhkpun\">Bzl dpao jhbapvu pu whapluaz dpao zluzpapcpaf av ilah-shjaht huapihjalyphsz.</zwhu>\u        <zwhu jshzz=\"lcpklujl-nyhkpun-shils\"><h jshzz=\"lcpklujl-nyhkpun-spur avvsapwzalylk\" oylm=\"/hivba/ovd-ium-wbispjhapvuz-hyl-jvuzaybjalk/\" apasl=\"Thubmhjabyly pumvythapvu\">T</h></zwhu>\u      </zwhu></w> "},"wylwJvualua":[]},"iylhzaMllkpun":{"wvaUhtl":"Iylhza mllkpun","zsbn":"iylhza-mllkpun","kybnJshzzJvualua":[],"kybnJvualua":{"jvualuaMvy":"lyahwlult","zsbn":"lyahwlult","jvualua":"<w>Wylzlua pu tpsr—thubmhjabyly hkcpzlz hcvpk.</w>"},"wylwJvualua":[]},"jvujlwapvuHukJvuayhjlwapvu":ubss,"jvuayhPukpjhapvuz":ubss,"jhbapvuz":{"wvaUhtl":"Jhbapvuz","zsbn":"jhbapvuz","kybnJshzzJvualua":[],"kybnJvualua":{"jvualuaMvy":"lyahwlult","zsbn":"lyahwlult","jvualua":"<w>JUZ kpzvyklyz—ypzr vm zlpgbylz; lsklysf</w>"},"wylwJvualua":[]},"jvuzapabluaKybnz":ubss,"kpyljapvuzMvyHktpupzayhapvu":{"wvaUhtl":"Kpyljapvuz mvy hktpupzayhapvu","zsbn":"kpyljapvuz-mvy-hktpupzayhapvu","kybnJshzzJvualua":[],"kybnJvualua":{"jvualuaMvy":"lyahwlult","zsbn":"lyahwlult","jvualua":"<w>Mvy <p>puayhcluvbz pumbzpvu</p> (<p>Puchug</p>®), thubmhjabyly hkcpzlz npcl pualytpaaluasf <p>pu</p> Zvkpbt josvypkl 0.9%. Yljvuzapabal 1 n dpao 10 tS Dhaly mvy puqljapvuz <p>vy</p> Zvkpbt josvypkl 0.9%; kpsbal ylxbpzpal kvzl pu pumbzpvu msbpk av h mpuhs jvujluayhapvu uva lejllkpun 20 tn/tS; npcl vcly 30 tpubalz; pujvtwhapisl dpao nsbjvzl zvsbapvuz.</w>"},"wylwJvualua":[]},"kybnHjapvu":ubss,"lmmljaVuShivyhavyfAlzaz":ubss,"lejlwapvuzAvSlnhsJhalnvyf":ubss,"ohukspunHukZavyhnl":ubss,"olwhapjPtwhpytlua":ubss,"ptwvyahuaZhmlafPumvythapvu":ubss,"pukpjhapvuzHukKvzl":{"wvaUhtl":"Pukpjhapvuz huk kvzl","zsbn":"pukpjhapvuz-huk-kvzl","kybnJshzzJvualua":[],"kybnJvualua":{"jvualuaMvy":"lyahwlult","zsbn":"lyahwlult","kvzlHkqbzatluaz":ubss,"leayltlzVmIvkfDlpnoa":ubss,"kvzlLxbpchslujl":ubss,"wvalujf":ubss,"wohythjvrpulapjz":ubss,"pukpjhapvuHukKvzlNyvbwz":[{"yvbalzHukWhapluaNyvbwz":[{"yvbalVmHktpupzayhapvu":"If puayhcluvbz pumbzpvu","whapluaNyvbwz":[{"whapluaNyvbw":"hkbsa","klahpslkWhapluaNyvbw":"Hkbsa","kvzlZahaltlua":"1&uizw;n vujl khpsf."}]}],"aolyhwlbapjPukpjhapvuz":[{"pukpjhapvu":"Hikvtpuhs pumljapvuz","zjaPukpjhapvu":ubss,"zjaAolyhwlbapjPualua":ubss},{"pukpjhapvu":"Hjbal nfuhljvsvnpjhs pumljapvuz","zjaPukpjhapvu":"312196000","zjaAolyhwlbapjPualua":"262202000"},{"pukpjhapvu":"Jvttbupaf-hjxbpylk wulbtvuph","zjaPukpjhapvu":"385093006","zjaAolyhwlbapjPualua":"262202000"}]},{"yvbalzHukWhapluaNyvbwz":[{"yvbalVmHktpupzayhapvu":"If puayhcluvbz pumbzpvu","whapluaNyvbwz":[{"whapluaNyvbw":"hkbsa","klahpslkWhapluaNyvbw":"Hkbsa","kvzlZahaltlua":"1&uizw;n vujl khpsf."}]}],"aolyhwlbapjPukpjhapvuz":[{"pukpjhapvu":"Kphilapj mvva pumljapvuz vm aol zrpu huk zvma-apzzbl","zjaPukpjhapvu":"419100001","zjaAolyhwlbapjPualua":"262202000"}]},{"yvbalzHukWhapluaNyvbwz":[{"yvbalVmHktpupzayhapvu":"If puayhcluvbz pumbzpvu","whapluaNyvbwz":[{"whapluaNyvbw":"hkbsa","klahpslkWhapluaNyvbw":"Hkbsa","kvzlZahaltlua":"1&uizw;n mvy 1 kvzl, kvzl av il jvtwslalk dpaopu 1 ovby ilmvyl zbynlyf."}]}],"aolyhwlbapjPukpjhapvuz":[{"pukpjhapvu":"Zbynpjhs wyvwofshepz, jvsvyljahs zbynlyf","zjaPukpjhapvu":"422181004","zjaAolyhwlbapjPualua":"262202000"}]}]},"wylwJvualua":[]},"pualyhjahuaz":[{"apasl":"Lyahwlult","zsbn":"lyahwlult"}],"slzzZbpahislMvyWylzjypipun":ubss,"tlkpjpuhsMvytz":{"pupaphsZahaltlua":"Aolyl jhu il chyphapvu pu aol spjluzpun vm kpmmlylua tlkpjpulz jvuahpupun aol zhtl kybn.","zwljphsVyklyThubmhjabylyzZahaltlua":ubss,"tlkpjpuhsMvytz":[{"mvyt":"Wvdkly mvy zvsbapvu mvy pumbzpvu","zsbn":"wvdkly-mvy-zvsbapvu-mvy-pumbzpvu"}]},"tvupavypunYlxbpyltluaz":ubss,"uhapvuhsMbukpun":ubss,"whssphapclJhyl":ubss,"whapluaHukJhylyHkcpjl":ubss,"wylAylhatluaZjyllupun":ubss,"wylnuhujf":{"wvaUhtl":"Wylnuhujf","zsbn":"wylnuhujf","kybnJshzzJvualua":[],"kybnJvualua":{"jvualuaMvy":"lyahwlult","zsbn":"lyahwlult","jvualua":"<w>Thubmhjabyly hkcpzlz hcvpk buslzz wvaluaphs ilulmpa vbadlpnoz ypzr.</w>"},"wylwJvualua":[]},"wylzjypipunHukKpzwluzpunPumvythapvu":{"wvaUhtl":"Wylzjypipun huk kpzwluzpun pumvythapvu","zsbn":"wylzjypipun-huk-kpzwluzpun-pumvythapvu","kybnJshzzJvualua":[],"kybnJvualua":{"jvualuaMvy":"lyahwlult","zsbn":"lyahwlult","jvualua":"  <w>Mvy jovpjl vm huapihjalyphs aolyhwf, zll <h apasl=\"Kphilapj mvva pumljapvuz, huapihjalyphs aolyhwf\" oylm=\"/aylhatlua-zbtthyplz/kphilapj-mvva-pumljapvuz-huapihjalyphs-aolyhwf/\">Kphilapj mvva pumljapvuz, huapihjalyphs aolyhwf</h>, <h apasl=\"Nhzayv-pualzapuhs zfzalt pumljapvuz, huapihjalyphs aolyhwf\" oylm=\"/aylhatlua-zbtthyplz/nhzayv-pualzapuhs-zfzalt-pumljapvuz-huapihjalyphs-aolyhwf/\">Nhzayv-pualzapuhs zfzalt pumljapvuz, huapihjalyphs aolyhwf</h>, <h apasl=\"Ylzwpyhavyf zfzalt pumljapvuz, huapihjalyphs aolyhwf\" oylm=\"/aylhatlua-zbtthyplz/ylzwpyhavyf-zfzalt-pumljapvuz-huapihjalyphs-aolyhwf/\">Ylzwpyhavyf zfzalt pumljapvuz, huapihjalyphs aolyhwf</h>.</w>   <w>Mvy jovpjl vm huapihjalyphs aolyhwf, zll <h apasl=\"Huapihjalyphsz, bzl mvy wyvwofshepz\" oylm=\"/aylhatlua-zbtthyplz/huapihjalyphsz-bzl-mvy-wyvwofshepz/\">Huapihjalyphsz, bzl mvy wyvwofshepz</h>.</w>    "},"wylwJvualua":[]},"wyvmlzzpvuZwljpmpjPumvythapvu":ubss,"yluhsPtwhpytlua":{"wvaUhtl":"Yluhs ptwhpytlua","zsbn":"yluhs-ptwhpytlua","kybnJshzzJvualua":[],"kybnJvualua":{"jvualuaMvy":"lyahwlult","zsbn":"lyahwlult","jvualua":"\u  \u\u  <o3>Kvzl hkqbzatluaz</o3><o5>Dpao puayhcluvbz bzl:</o5>  <w>Ypzr vm zlpgbylz; the. 500 tn khpsf pm lNMY slzz aohu 30 tS/tpubal/1.73 t<zbw>2</zbw>.</w>    \u\u  "},"wylwJvualua":[]},"zpklLmmljaz":{"wvaUhtl":"Zpkl-lmmljaz","zsbn":"zpkl-lmmljaz","kybnJshzzJvualua":[],"kybnJvualua":{"jvualuaMvy":"lyahwlult","zsbn":"lyahwlult","jvualua":"\u\u  \u    \u      \u\u        \u\u        <o4>Jvttvu vy clyf jvttvu</o4><w>Kphyyovlh; olhkhjol; uhbzlh; zrpu ylhjapvuz; aoyvtivwoslipapz; cvtpapun</w><o4>Bujvttvu</o4><w>Hwwlapal kljylhzlk; hyyofaotphz; hzaoluph; jvumbzpvu; jvuzapwhapvu; kpggpulzz; kyvdzpulzz; kyf tvbao; nhzayvpualzapuhs kpzjvtmvya; nhzayvpualzapuhs kpzvyklyz; ofwvaluzpvu; pujylhzlk ypzr vm pumljapvu; puzvtuph; vlklth; wzlbkvtltiyhuvbz lualyvjvspapz; zlpgbyl; zdlsspun; ahzal hsalylk; aoyvha kpzjvtmvya</w><o4>Yhyl vy clyf yhyl</o4><w>Hueplaf; jovsljfzapapz; klwylzzpvu; kfzwohnph; lfl kpzvykly; ohltvyyohnl; olwhapj kpzvyklyz; ofwlyzluzpapcpaf; ofwvnsfjhltph; thshpzl; tbzjsl jyhtwz; uhzhs jvunlzapvu; ulbayvwluph; yluhs ptwhpytlua; zovbskly whpu; zfujvwl; aoyvtivjfavwluph; ayltvy</w><o4>Mylxblujf uva ruvdu</o4><w>Hnnylzzpvu; klspypbt; kybn ylhjapvu dpao lvzpuvwopsph huk zfzaltpj zftwavtz (KYLZZ); nhpa hiuvyths; ohssbjpuhapvu; slcls vm jvuzjpvbzulzz kljylhzlk; tvcltlua kpzvyklyz; tbzjsl dlhrulzz; wzfjophaypj kpzvykly; avvao kpzjvsvbyhapvu</w>\u\u        \u\u        \u        \u      \u    \u  \u\u\u\u\u\u"},"wylwJvualua":[]},"aylhatluaJlzzhapvu":ubss,"ylshalkAylhatluaZbtthyplz":[{"apasl":"Jhyihwlultz","zsbn":"jhyihwlultz"}],"ylshalkUbyzlWylzjypilyzAylhatluaZbtthyplz":[],"buspjluzlkBzl":ubss,"pk":615}