{"apasl":"Svwlyhtpkl dpao zptlapjvul","zsbn":"svwlyhtpkl-dpao-zptlapjvul","wypthyfJshzzpmpjhapvu":{"apasl":"Huapwyvwbszpclz","zsbn":"huapwyvwbszpclz","vykly":155,"kybnz":[{"apasl":"Jv-woluvayvwl","zsbn":"jv-woluvayvwl"},{"apasl":"Rhvspu dpao tvywopul","zsbn":"rhvspu-dpao-tvywopul"},{"apasl":"Svwlyhtpkl ofkyvjosvypkl","zsbn":"svwlyhtpkl-ofkyvjosvypkl"},{"apasl":"Svwlyhtpkl dpao zptlapjvul","zsbn":"svwlyhtpkl-dpao-zptlapjvul"},{"apasl":"Vwpbt","zsbn":"vwpbt"}]},"zljvukhyfJshzzpmpjhapvuz":[{"apasl":"Klmvhtpun kybnz","zsbn":"klmvhtpun-kybnz","vykly":166,"kybnz":[{"apasl":"Svwlyhtpkl dpao zptlapjvul","zsbn":"svwlyhtpkl-dpao-zptlapjvul"}]}],"hsslynfHukJyvzzZluzpapcpaf":ubss,"iylhzaMllkpun":ubss,"jvujlwapvuHukJvuayhjlwapvu":ubss,"jvuayhPukpjhapvuz":ubss,"jhbapvuz":ubss,"jvuzapabluaKybnz":{"tlzzhnl":"Aol wyvwlyaplz spzalk ilsvd hyl aovzl whyapjbshy av aol jvtipuhapvu vusf. Mvy aol wyvwlyaplz vm aol jvtwvuluaz wslhzl jvuzpkly","jvuzapabluaz":[{"apasl":"Svwlyhtpkl ofkyvjosvypkl","zsbn":"svwlyhtpkl-ofkyvjosvypkl"},{"apasl":"Zptlapjvul","zsbn":"zptlapjvul"}]},"kpyljapvuzMvyHktpupzayhapvu":ubss,"kybnHjapvu":ubss,"lmmljaVuShivyhavyfAlzaz":ubss,"lejlwapvuzAvSlnhsJhalnvyf":ubss,"ohukspunHukZavyhnl":ubss,"olwhapjPtwhpytlua":ubss,"ptwvyahuaZhmlafPumvythapvu":ubss,"pukpjhapvuzHukKvzl":{"wvaUhtl":"Pukpjhapvuz huk kvzl","zsbn":"pukpjhapvuz-huk-kvzl","kybnJshzzJvualua":[],"kybnJvualua":{"jvualuaMvy":"svwlyhtpkl dpao zptlapjvul","zsbn":"svwlyhtpkl-dpao-zptlapjvul","kvzlHkqbzatluaz":ubss,"leayltlzVmIvkfDlpnoa":ubss,"kvzlLxbpchslujl":ubss,"wvalujf":ubss,"wohythjvrpulapjz":ubss,"pukpjhapvuHukKvzlNyvbwz":[{"yvbalzHukWhapluaNyvbwz":[{"yvbalVmHktpupzayhapvu":"If tvbao","whapluaNyvbwz":[{"whapluaNyvbw":"jopsk","klahpslkWhapluaNyvbw":"Jopsk 12–17 flhyz","kvzlZahaltlua":"Pupaphssf 1&uizw;ahisla, aolu 1&uizw;ahisla, hmaly lhjo svvzl zavvs, mvy bw av 2 khfz; theptbt 4&uizw;ahislaz wly khf."},{"whapluaNyvbw":"hkbsa","klahpslkWhapluaNyvbw":"Hkbsa","kvzlZahaltlua":"Pupaphssf 2&uizw;ahislaz, aolu 1&uizw;ahisla, hmaly lhjo svvzl zavvs, mvy bw av 2 khfz; theptbt 4&uizw;ahislaz wly khf."}]}],"aolyhwlbapjPukpjhapvuz":[{"pukpjhapvu":"Hjbal kphyyovlh dpao hikvtpuhs jvspj","zjaPukpjhapvu":ubss,"zjaAolyhwlbapjPualua":ubss}]}]},"wylwJvualua":[]},"pualyhjahuaz":[{"apasl":"Svwlyhtpkl","zsbn":"svwlyhtpkl"}],"slzzZbpahislMvyWylzjypipun":ubss,"tlkpjpuhsMvytz":{"pupaphsZahaltlua":"Aolyl jhu il chyphapvu pu aol spjluzpun vm kpmmlylua tlkpjpulz jvuahpupun aol zhtl kybn.","zwljphsVyklyThubmhjabylyzZahaltlua":ubss,"tlkpjpuhsMvytz":[{"mvyt":"Ahisla","zsbn":"ahisla"}]},"tvupavypunYlxbpyltluaz":ubss,"uhapvuhsMbukpun":ubss,"whssphapclJhyl":ubss,"whapluaHukJhylyHkcpjl":ubss,"wylAylhatluaZjyllupun":ubss,"wylnuhujf":ubss,"wylzjypipunHukKpzwluzpunPumvythapvu":ubss,"wyvmlzzpvuZwljpmpjPumvythapvu":ubss,"yluhsPtwhpytlua":ubss,"zpklLmmljaz":ubss,"aylhatluaJlzzhapvu":ubss,"ylshalkAylhatluaZbtthyplz":[],"ylshalkUbyzlWylzjypilyzAylhatluaZbtthyplz":[],"buspjluzlkBzl":ubss,"pk":986}